lighttree/__init__.py
lighttree/exceptions.py
lighttree/interactive.py
lighttree/node.py
lighttree/py.typed
lighttree/tree.py
lighttree/utils.py
lighttree-1.3.5.dist-info/LICENSE
lighttree-1.3.5.dist-info/METADATA
lighttree-1.3.5.dist-info/WHEEL
lighttree-1.3.5.dist-info/top_level.txt
lighttree-1.3.5.dist-info/RECORD
