Metadata-Version: 2.1
Name: lighttree
Version: 1.3.5
Summary: UNKNOWN
Home-page: https://github.com/leonardbinet/lighttree
Author: Léonard Binet
Author-email: leonardbinet@gmail.com
License: MIT
Keywords: tree,interactive
Platform: UNKNOWN
License-File: LICENSE
Provides-Extra: develop
Requires-Dist: pre-commit ; extra == 'develop'
Requires-Dist: black ; extra == 'develop'
Requires-Dist: flake8 ; extra == 'develop'
Requires-Dist: mock ; extra == 'develop'
Requires-Dist: coverage ; extra == 'develop'
Requires-Dist: pytest ; extra == 'develop'
Requires-Dist: mypy ; extra == 'develop'
Requires-Dist: twine ; extra == 'develop'
